amira/__init__.py
amira/__main__.py
amira/construct_edge.py
amira/construct_gene.py
amira/construct_gene_mer.py
amira/construct_graph.py
amira/construct_node.py
amira/construct_read.py
amira/graph_operations.py
amira/path_finding_operations.py
amira/pre_process_operations.py
amira/read_operations.py
amira/result_operations.py
amira_amr-0.4.1.dist-info/LICENSE
amira_amr-0.4.1.dist-info/METADATA
amira_amr-0.4.1.dist-info/WHEEL
amira_amr-0.4.1.dist-info/entry_points.txt
amira_amr-0.4.1.dist-info/RECORD
