Metadata-Version: 2.1
Name: amira-amr
Version: 0.4.1
Summary: Amira
Home-page: https://github.com/Danderson123/amira
License: Apache-2.0
Keywords: AMR Prediction,Genotyping,Sequence Assembly
Author: Daniel Anderson
Author-email: dander@ebi.ac.uk
Requires-Python: >=3.9,<3.13
Classifier: License :: OSI Approved :: Apache Software License
Classifier: Programming Language :: Python :: 3
Classifier: Programming Language :: Python :: 3.9
Classifier: Programming Language :: Python :: 3.10
Classifier: Programming Language :: Python :: 3.11
Classifier: Programming Language :: Python :: 3.12
Requires-Dist: joblib (==1.2.0)
Requires-Dist: matplotlib (==3.6.2)
Requires-Dist: pandas (==2.2.2)
Requires-Dist: pysam (==0.22.0)
Requires-Dist: pytest (==7.2.0)
Requires-Dist: scipy (==1.12.0)
Requires-Dist: setuptools (==75.3.0)
Requires-Dist: sourmash (==4.8.4)
Requires-Dist: suffix-tree (==0.1.2)
Requires-Dist: tqdm (==4.66.3)
Project-URL: Repository, https://github.com/Danderson123/amira
